odoo/addons/ssi_accountant/README.rst
odoo/addons/ssi_accountant/__init__.py
odoo/addons/ssi_accountant/__manifest__.py
odoo/addons/ssi_accountant/menu.xml
odoo/addons/ssi_accountant/demo/accountant_financial_accounting_standard_demo.xml
odoo/addons/ssi_accountant/demo/accountant_opinion_demo.xml
odoo/addons/ssi_accountant/demo/accountant_service_demo.xml
odoo/addons/ssi_accountant/models/__init__.py
odoo/addons/ssi_accountant/models/accountant_financial_accounting_standard.py
odoo/addons/ssi_accountant/models/accountant_opinion.py
odoo/addons/ssi_accountant/models/accountant_service.py
odoo/addons/ssi_accountant/models/res_company.py
odoo/addons/ssi_accountant/models/res_config_settings.py
odoo/addons/ssi_accountant/models/res_partner_industry.py
odoo/addons/ssi_accountant/security/ir.model.access.csv
odoo/addons/ssi_accountant/security/ir_module_category_data.xml
odoo/addons/ssi_accountant/security/res_group_data.xml
odoo/addons/ssi_accountant/static/description/icon.png
odoo/addons/ssi_accountant/views/accountant_financial_accounting_standard_views.xml
odoo/addons/ssi_accountant/views/accountant_opinion_views.xml
odoo/addons/ssi_accountant/views/accountant_service_views.xml
odoo/addons/ssi_accountant/views/res_config_settings_views.xml
odoo/addons/ssi_accountant/views/res_partner_industry_views.xml
odoo14_addon_ssi_accountant-14.0.2.3.0.dist-info/METADATA
odoo14_addon_ssi_accountant-14.0.2.3.0.dist-info/WHEEL
odoo14_addon_ssi_accountant-14.0.2.3.0.dist-info/top_level.txt
odoo14_addon_ssi_accountant-14.0.2.3.0.dist-info/RECORD
